{"cameraMode":{"drawMode":0,"name":"Shaded","section":"Shading Mode"},"sceneLighting":false,"audioPlay":false,"sceneViewState":{"m_AlwaysRefresh":false,"showFog":true,"showSkybox":false,"showFlares":true,"showImageEffects":true,"showParticleSystems":true,"showVisualEffectGraphs":true,"m_FxEnabled":true},"in2DMode":false,"pivot":{"x":0.0,"y":0.05154228210449219,"z":0.0},"rotation":{"x":-0.4433402419090271,"y":-0.20135238766670228,"z":0.10289301723241806,"w":-0.8673897385597229},"size":0.8660253882408142,"orthographic":false}